{
  "content": {
    "application/json": {
      "schema": {
        "type": "object",
        "properties": {
          "code_type": {
            "type": "string",
            "enum": [
              "EmailRegistration",
              "PhoneRegistration",
              "EmailUpdate",
              "PhoneUpdate"
            ]
          },
          "owner": {
            "type": "string",
            "example": "test-admin@test.com"
          },
          "user_key": {
            "type": "string",
            "additionalProperties": true
          }
        },
        "required": [
          "code_type",
          "owner"
        ]
      },
      "examples": {
        "Get Register Email Code": {
          "value": {
            "code_type": "EmailRegistration",
            "owner": "test-admin@test.com"
          }
        },
        "Get Update Email Code": {
          "value": {
            "code_type": "EmailUpdate",
            "owner": "test-admin@test.com"
          }
        }
      }
    }
  }
}